{
    "产品名称": {
        "标准版": "Smart LXP™标准版",
        "专业版": "Smart LXP™专业版",
        "全球版": "Smart LXP™全球版"
    },
    "价格体系": {
        "刊例价": {
            "标准版": "399元/账号",
            "专业版": "999元/账号",
            "全球版": "1199元/账号"
        },
        "报价方式": {
            "标准版": "固定价",
            "专业版": "阶梯价",
            "全球版": "阶梯价"
        },
        "起售数": {
            "标准版": "10个起售",
            "专业版": "50个起售",
            "全球版": "50个起售"
        }
    },
    "课程资源": {
        "课程数量": {
            "标准版": "全量 (6000+门)",
            "专业版": "全量 (6000+门)",
            "全球版": "全量 (6000+门)"
        },
        "精选专题": {
            "标准版": "✓",
            "专业版": "✓",
            "全球版": "✓"
        },
        "课程更新服务": {
            "标准版": "✓ (平均每月更新100+门)",
            "专业版": "✓ (平均每月更新100+门)",
            "全球版": "✓ (平均每月更新100+门)"
        },
        "在线答疑服务": {
            "标准版": "✓",
            "专业版": "✓",
            "全球版": "✓"
        },
        "认证课程": {
            "标准版": "-",
            "专业版": "✓",
            "全球版": "✓"
        }
    },
    "系统功能": {
        "系统管理员": {
            "标准版": "✓",
            "专业版": "✓",
            "全球版": "✓"
        },
        "课程上传": {
            "标准版": "✓",
            "专业版": "✓",
            "全球版": "✓"
        },
        "学习路径": {
            "标准版": "✓",
            "专业版": "✓",
            "全球版": "✓"
        },
        "基础数据分析": {
            "标准版": "✓",
            "专业版": "✓",
            "全球版": "✓"
        },
        "技能洞察看板": {
            "标准版": "-",
            "专业版": "✓",
            "全球版": "✓"
        },
        "数据大屏看板": {
            "标准版": "-",
            "专业版": "✓",
            "全球版": "✓"
        },
        "个性化页面配置": {
            "标准版": "-",
            "专业版": "✓",
            "全球版": "✓"
        }
    },
    "AI能力": {
        "AI测验": {
            "标准版": "✓",
            "专业版": "✓",
            "全球版": "✓"
        },
        "AI视频总结": {
            "标准版": "✓",
            "专业版": "✓",
            "全球版": "✓"
        },
        "AI字幕": {
            "标准版": "✓",
            "专业版": "✓",
            "全球版": "✓"
        },
        "AI课程推荐智能体": {
            "标准版": "✓",
            "专业版": "✓",
            "全球版": "✓"
        },
        "AI技能洞察智能体": {
            "标准版": "-",
            "专业版": "✓",
            "全球版": "✓"
        }
    },
    "平台对接": {
        "登录方式授权": {
            "标准版": "钉钉/企微/飞书/手机/邮箱/微信",
            "专业版": "除此标准版之外,SSO/OAuth2.0",
            "全球版": "除此标准版之外,SSO/OAuth2.0"
        },
        "第三方接口 (eHR/OA/学习平台)": {
            "标准版": "-",
            "专业版": "✓",
            "全球版": "✓"
        }
    },
    "客户成功服务": {
        "在线客服": {
            "标准版": "✓",
            "专业版": "✓",
            "全球版": "✓"
        },
        "学习路径定制": {
            "标准版": "-",
            "专业版": "✓",
            "全球版": "✓"
        },
        "客户专属答疑": {
            "标准版": "-",
            "专业版": "✓",
            "全球版": "✓"
        },
        "学习运营支持": {
            "标准版": "-",
            "专业版": "✓",
            "全球版": "✓"
        },
        "学习报告解读": {
            "标准版": "-",
            "专业版": "✓",
            "全球版": "✓"
        }
    },
    "多语言支持": {
        "系统双语界面": {
            "标准版": "-",
            "专业版": "-",
            "全球版": "✓"
        },
        "多语言字幕": {
            "标准版": "-",
            "专业版": "-",
            "全球版": "✓"
        },
        "多语言课程包": {
            "标准版": "-",
            "专业版": "-",
            "全球版": "✓"
        }
    }
}

